COPYING
COPYING.lesser
MANIFEST.in
NOTICE
README.md
requirements.txt
setup.py
Nerogram.egg-info/PKG-INFO
Nerogram.egg-info/SOURCES.txt
Nerogram.egg-info/dependency_links.txt
Nerogram.egg-info/not-zip-safe
Nerogram.egg-info/requires.txt
Nerogram.egg-info/top_level.txt
compiler/__init__.py
compiler/api/__init__.py
compiler/api/compiler.py
compiler/api/source/auth_key.tl
compiler/api/source/main_api.tl
compiler/api/source/sys_msgs.tl
compiler/api/template/combinator.txt
compiler/api/template/type.txt
compiler/docs/__init__.py
compiler/docs/compiler.py
compiler/docs/template/page.txt
compiler/docs/template/toctree.txt
compiler/errors/__init__.py
compiler/errors/compiler.py
compiler/errors/sort.py
compiler/errors/source/303_SEE_OTHER.tsv
compiler/errors/source/400_BAD_REQUEST.tsv
compiler/errors/source/401_UNAUTHORIZED.tsv
compiler/errors/source/403_FORBIDDEN.tsv
compiler/errors/source/406_NOT_ACCEPTABLE.tsv
compiler/errors/source/420_FLOOD.tsv
compiler/errors/source/500_INTERNAL_SERVER_ERROR.tsv
compiler/errors/source/503_SERVICE_UNAVAILABLE.tsv
compiler/errors/template/class.txt
compiler/errors/template/sub_class.txt
nerogram/__init__.py
nerogram/client.py
nerogram/dispatcher.py
nerogram/emoji.py
nerogram/file_id.py
nerogram/filters.py
nerogram/mime_types.py
nerogram/py.typed
nerogram/sync.py
nerogram/utils.py
nerogram/connection/__init__.py
nerogram/connection/connection.py
nerogram/connection/transport/__init__.py
nerogram/connection/transport/tcp/__init__.py
nerogram/connection/transport/tcp/tcp.py
nerogram/connection/transport/tcp/tcp_abridged.py
nerogram/connection/transport/tcp/tcp_abridged_o.py
nerogram/connection/transport/tcp/tcp_full.py
nerogram/connection/transport/tcp/tcp_intermediate.py
nerogram/connection/transport/tcp/tcp_intermediate_o.py
nerogram/crypto/__init__.py
nerogram/crypto/aes.py
nerogram/crypto/mtproto.py
nerogram/crypto/prime.py
nerogram/crypto/rsa.py
nerogram/enums/__init__.py
nerogram/enums/auto_name.py
nerogram/enums/chat_action.py
nerogram/enums/chat_event_action.py
nerogram/enums/chat_member_status.py
nerogram/enums/chat_members_filter.py
nerogram/enums/chat_type.py
nerogram/enums/message_entity_type.py
